hpargparse/__init__.py
hpargparse/config.py
hpargparse/hputils.py
hpargparse/pkginfo.py
hpargparse-0.14.0.data/scripts/hpcli
hpargparse-0.14.0.dist-info/LICENSE
hpargparse-0.14.0.dist-info/METADATA
hpargparse-0.14.0.dist-info/WHEEL
hpargparse-0.14.0.dist-info/top_level.txt
hpargparse-0.14.0.dist-info/RECORD
