Metadata-Version: 2.1
Name: hpargparse
Version: 0.14.0
Summary: An argparse extension for hpman
Home-page: https://github.com/megvii-research/hpargparse
Author: Xinyu Zhou
Author-email: zxy@megvii.com
Classifier: Programming Language :: Python :: 3
Classifier: License :: OSI Approved :: MIT License
Classifier: Operating System :: OS Independent
Classifier: Intended Audience :: Developers
Classifier: Intended Audience :: Science/Research
Classifier: Topic :: Scientific/Engineering :: Artificial Intelligence
Classifier: Topic :: Software Development :: Libraries :: Python Modules
License-File: LICENSE
Requires-Dist: rich
Requires-Dist: dill
Requires-Dist: hpman (>=0.0.6)
Requires-Dist: PyYAML
